archook/VERSION
archook/__init__.py
archook/archook.py
archook_dbc-202202.1.2045.dist-info/LICENSE
archook_dbc-202202.1.2045.dist-info/METADATA
archook_dbc-202202.1.2045.dist-info/WHEEL
archook_dbc-202202.1.2045.dist-info/top_level.txt
archook_dbc-202202.1.2045.dist-info/RECORD
