Metadata-Version: 2.1
Name: archook_dbc
Version: 202202.1.2045
Summary: Locates arcpy and makes it available to the running python distribution
Home-page: https://github.com/JamesRamm/archook
Author: James Ramm
Author-email: nospam@example.com
Maintainer: Matt Wilkie
Maintainer-email: matt.wilkie@gov.yk.ca
License: UNKNOWN
Keywords: ArcGIS,arcpy
Platform: UNKNOWN
Classifier: Development Status :: 4 - Beta
Classifier: Environment :: Console
Classifier: Intended Audience :: Science/Research
Classifier: License :: OSI Approved :: GNU General Public License v2 (GPLv2)
Classifier: Programming Language :: Python :: 2.7
Classifier: Programming Language :: Python :: 3
Classifier: Topic :: Scientific/Engineering
Classifier: Operating System :: Microsoft :: Windows
License-File: LICENSE
